sbdh_ubl_data/__init__.py
sbdh_ubl_data/sbdh/__init__.py
sbdh_ubl_data/sbdh/business_scope.py
sbdh_ubl_data/sbdh/document_identification.py
sbdh_ubl_data/sbdh/manifest.py
sbdh_ubl_data/sbdh/order.py
sbdh_ubl_data/sbdh/order_response.py
sbdh_ubl_data/sbdh/partner.py
sbdh_ubl_data/sbdh/standard_business_document_header.py
sbdh_ubl_data/ubl/__init__.py
sbdh_ubl_data/ubl/common/__init__.py
sbdh_ubl_data/ubl/common/ccts_cct_schema_module_2_1.py
sbdh_ubl_data/ubl/common/ubl_common_aggregate_components_2_1.py
sbdh_ubl_data/ubl/common/ubl_common_basic_components_2_1.py
sbdh_ubl_data/ubl/common/ubl_common_extension_components_2_1.py
sbdh_ubl_data/ubl/common/ubl_common_signature_components_2_1.py
sbdh_ubl_data/ubl/common/ubl_extension_content_data_type_2_1.py
sbdh_ubl_data/ubl/common/ubl_signature_aggregate_components_2_1.py
sbdh_ubl_data/ubl/common/ubl_signature_basic_components_2_1.py
sbdh_ubl_data/ubl/common/ubl_unqualified_data_types_2_1.py
sbdh_ubl_data/ubl/common/ubl_xad_esv132_2_1.py
sbdh_ubl_data/ubl/common/ubl_xad_esv141_2_1.py
sbdh_ubl_data/ubl/common/ubl_xmldsig_core_schema_2_1.py
sbdh_ubl_data/ubl/maindoc/__init__.py
sbdh_ubl_data/ubl/maindoc/ubl_application_response_2_1.py
sbdh_ubl_data/ubl/maindoc/ubl_attached_document_2_1.py
sbdh_ubl_data/ubl/maindoc/ubl_awarded_notification_2_1.py
sbdh_ubl_data/ubl/maindoc/ubl_bill_of_lading_2_1.py
sbdh_ubl_data/ubl/maindoc/ubl_call_for_tenders_2_1.py
sbdh_ubl_data/ubl/maindoc/ubl_catalogue_2_1.py
sbdh_ubl_data/ubl/maindoc/ubl_catalogue_deletion_2_1.py
sbdh_ubl_data/ubl/maindoc/ubl_catalogue_item_specification_update_2_1.py
sbdh_ubl_data/ubl/maindoc/ubl_catalogue_pricing_update_2_1.py
sbdh_ubl_data/ubl/maindoc/ubl_catalogue_request_2_1.py
sbdh_ubl_data/ubl/maindoc/ubl_certificate_of_origin_2_1.py
sbdh_ubl_data/ubl/maindoc/ubl_contract_award_notice_2_1.py
sbdh_ubl_data/ubl/maindoc/ubl_contract_notice_2_1.py
sbdh_ubl_data/ubl/maindoc/ubl_credit_note_2_1.py
sbdh_ubl_data/ubl/maindoc/ubl_debit_note_2_1.py
sbdh_ubl_data-0.1.1.dist-info/LICENSE
sbdh_ubl_data-0.1.1.dist-info/WHEEL
sbdh_ubl_data-0.1.1.dist-info/METADATA
sbdh_ubl_data-0.1.1.dist-info/RECORD
