Metadata-Version: 2.1
Name: sbdh-ubl-data
Version: 0.1.1
Summary: 
Author: Anders Lehn Reed
Author-email: anders.lehn.reed@gmail.com
Requires-Python: >=3.10,<4.0
Classifier: Programming Language :: Python :: 3
Classifier: Programming Language :: Python :: 3.10
Requires-Dist: xsdata (>=25.4,<26.0)
